ak/config.py
akconfig-0.1.12.dist-info/LICENSE
akconfig-0.1.12.dist-info/METADATA
akconfig-0.1.12.dist-info/WHEEL
akconfig-0.1.12.dist-info/entry_points.txt
akconfig-0.1.12.dist-info/RECORD
