Metadata-Version: 2.3
Name: akconfig
Version: 0.1.12
Summary: A configuration management for global variables in python projects.
License: MIT
Author: dapk
Author-email: dapk@gmx.net
Requires-Python: >=3.9,<4.0
Classifier: License :: OSI Approved :: MIT License
Classifier: Programming Language :: Python :: 3
Classifier: Programming Language :: Python :: 3.9
Classifier: Programming Language :: Python :: 3.10
Classifier: Programming Language :: Python :: 3.11
Classifier: Programming Language :: Python :: 3.12
Classifier: Programming Language :: Python :: 3.13
Requires-Dist: colored (>=2.2.5)
Requires-Dist: terminaltables (>=3.1.10)
Project-URL: Homepage, https://github.com/dapkdapk/akconfig
Project-URL: Repository, https://github.com/dapkdapk/akconfig
Project-URL: Source Code, https://github.com/dapkdapk/akconfig.git
